pdf_image_text9_test/__init__.py
pdf_image_text9_test/processor.py
pdf_image_text9_test/schema.py
pdf_image_text9_test/script.py
pdf_image_text9_test-0.1.9.dist-info/LICENCE
pdf_image_text9_test-0.1.9.dist-info/METADATA
pdf_image_text9_test-0.1.9.dist-info/WHEEL
pdf_image_text9_test-0.1.9.dist-info/RECORD
