Metadata-Version: 2.1
Name: pdf-image-text9-test
Version: 0.1.9
Summary: A python package to generate text from pdf and images
License: LICENCE
Keywords: test,dependencies,documentation
Author: Devesh Singh
Author-email: devesh.singh@bain.com
Requires-Python: >=3.8,<4.0
Classifier: Development Status :: 5 - Production/Stable
Classifier: Intended Audience :: Developers
Classifier: License :: OSI Approved :: MIT License
Classifier: License :: Other/Proprietary License
Classifier: Operating System :: OS Independent
Classifier: Programming Language :: Python :: 3
Classifier: Programming Language :: Python :: 3.8
Classifier: Programming Language :: Python :: 3.9
Classifier: Programming Language :: Python :: 3.10
Classifier: Programming Language :: Python :: 3.11
Classifier: Programming Language :: Python :: 3.12
Requires-Dist: filetype (==1.2.0)
Requires-Dist: pydantic (==2.6.3)
Requires-Dist: pymupdf (>=1.22.0,<2.0.0)
Requires-Dist: requests (==2.31.0)
